lordkelvin/__init__.py
lordkelvin/__main__.py
lordkelvin/contracts/IWETH9.sol
lordkelvin/contracts/Test2.sol
lordkelvin/contracts/erc20.sol
lordkelvin/scripts/env.ganache.sh
lordkelvin/scripts/env.kovan.sh
lordkelvin/scripts/env.sh
lordkelvin/scripts/launch_ganache.py
lordkelvin/scripts/makex
lordkelvin/scripts/solc.sh
lordkelvin/tools/Dockerfile.Darwin
lordkelvin/tools/Dockerfile.Linux
lordkelvin/tools/Dockerfile.lkh
lordkelvin/tools/Makefile
lordkelvin/tools/aliases
lordkelvin/tools/app.js
lordkelvin/tools/collapse.py
lordkelvin/tools/download.sh
lordkelvin/tools/init.el
lordkelvin-3.8.1.data/scripts/env.ganache.sh
lordkelvin-3.8.1.data/scripts/env.kovan.sh
lordkelvin-3.8.1.data/scripts/env.sh
lordkelvin-3.8.1.data/scripts/launch_ganache.py
lordkelvin-3.8.1.data/scripts/makex
lordkelvin-3.8.1.data/scripts/solc.sh
lordkelvin-3.8.1.dist-info/LICENSE
lordkelvin-3.8.1.dist-info/METADATA
lordkelvin-3.8.1.dist-info/WHEEL
lordkelvin-3.8.1.dist-info/entry_points.txt
lordkelvin-3.8.1.dist-info/top_level.txt
lordkelvin-3.8.1.dist-info/zip-safe
lordkelvin-3.8.1.dist-info/RECORD
