Metadata-Version: 2.1
Name: lordkelvin
Version: 3.8.1
Summary: super cool toolkit
Home-page: https://gitlab.com/circleclicklabs/lordkelvin.git
Author: Joel Ward
Author-email: jmward+python@gmail.com
License: MIT
Platform: UNKNOWN
Classifier: Programming Language :: Python :: 3
Classifier: License :: OSI Approved :: MIT License
Classifier: Operating System :: OS Independent
License-File: LICENSE
Requires-Dist: docopt
Requires-Dist: web3 (==5.24)
Requires-Dist: eth-account
